<?xml version="1.0"?>
<pets><pet><id>1</id><name>Buddy</name><category>dog</category><status>available</status><imageName>buddy.jpg</imageName></pet><pet><id>2</id><name>Milo</name><category>cat</category><status>adopted</status><imageName>milo.jpg</imageName></pet><pet><id>3</id><name>Charlie</name><category>dog</category><status>dead</status><imageName>charlie.jpg</imageName></pet><pet><id>4</id><name>Bella</name><category>cat</category><status>pending</status><imageName>bella.jpg</imageName></pet><pet><id>5</id><name>Luna</name><category>dog</category><status>available</status><imageName>luna.jpg</imageName></pet><pet><id>6</id><name>Max</name><category>dog</category><status>adopted</status><imageName>max.jpg</imageName></pet><pet><id>7</id><name>Lucy</name><category>cat</category><status>available</status><imageName>lucy.jpg</imageName></pet><pet><id>8</id><name>Daisy</name><category>dog</category><status>available</status><imageName>daisy.jpg</imageName></pet><pet><id>9</id><name>Rocky</name><category>dog</category><status>pending</status><imageName>rocky.jpg</imageName></pet><pet><id>15</id><name>as</name><category>vtak</category><status>dead</status><imageName>IMG_0361.jpeg</imageName></pet><pet><id>18</id><name>as</name><category>vtak</category><status>dead</status><imageName/></pet><pet><id>19</id><name>as</name><category>vtak</category><status>dead</status><imageName/></pet><pet><id>20</id><name>as</name><category>vtak</category><status>dead</status><imageName/></pet><pet><id>21</id><name>as</name><category>vtak</category><status>dead</status><imageName>pet66ded4501012ajpeg</imageName></pet><pet><id>22</id><name>as</name><category>vtakkkkk</category><status>dead</status><imageName>pet66ded451c1e72jpeg</imageName></pet><pet><id>24</id><name>daf</name><category>cat</category><status>deadxx</status><imageName/></pet><pet><id>28</id><name>dvadsat</name><category>cat</category><status>live</status><imageName/></pet></pets>
